pipelineCPU/pipelineCPU.srcs/sources_1/new/InputModule.v
`timescale 1ns / 1ps

module InputModule(
    input clk,
    input clk_de,
    input rst,
    input [7:0] sw_input,
    input done,
    output [31:0] input_data,
    output reg done_input
    );
    assign input_data = {{24{sw_input[7]}},sw_input};
    parameter DEBOUNCE_THRESHOLD = 4'b0001;  
    reg done_stable;
    reg [3:0] done_counter;
    reg next_done_input, period_done, next_period_done;

    always @(posedge clk_de , negedge rst) begin
        if(~rst) begin
            done_stable <= 0;
        end else begin
            if (done) begin
                if (done_counter < DEBOUNCE_THRESHOLD) begin
                    done_counter <= done_counter + 1;
                end else begin
                    done_stable <= 1;
                end
            end else begin
                done_counter <= 0;
                done_stable <= 0;
            end
        end
    end
    
    always @(posedge clk, negedge rst) begin
        if(~rst) begin
            done_input <= 0;
            period_done <= 0;
        end else begin
            done_input <= next_done_input;
            period_done <= next_period_done;
        end
    end
    
    always @(*) begin
        if (done_stable) begin
            if(done_input) begin
                next_period_done = 1;
                next_done_input = 0;
            end else begin
                next_period_done = period_done;
                if(~period_done) begin
                    next_done_input =1;
                end else begin
                    next_done_input = 0;
                end
            end
        end else begin
            next_period_done = 0;
            next_done_input = 0;
        end
    end
endmodule

pipelineCPU/pipelineCPU.srcs/sim_1/new/tb_InputModule.v
`timescale 1ns / 1ps

module tb_InputModule;

  // inputs
  reg        clk;
  reg        clk_de;
  reg        rst;
  reg  [7:0] sw_input;
  reg        done;

  // outputs
  wire [31:0] input_data;
  wire        done_input;

  // instantiate DUT
  InputModule uut (
    .clk        (clk),
    .clk_de     (clk_de),
    .rst        (rst),
    .sw_input   (sw_input),
    .done       (done),
    .input_data (input_data),
    .done_input (done_input)
  );

  // 100 MHz main clock
  initial clk = 0;
  always #5 clk = ~clk;

  // 1 MHz debounce clock
  initial clk_de = 0;
  always #500 clk_de = ~clk_de;

  initial begin
    // waveform dump
    $dumpfile("tb_InputModule.vcd");
    $dumpvars(0, tb_InputModule);

    // apply reset
    rst = 0; done = 0; sw_input = 8'h00;
    #20;
    rst = 1;

    // test sign-extension of sw_input
    sw_input = 8'hF0;  #10;
    if (input_data !== 32'hFFFF_FFF0) $fatal("Sign-ext failed");

    sw_input = 8'h7A;  #10;
    if (input_data !== 32'h0000_007A) $fatal("Zero-ext fail");

    // test done debounce: short glitch (< threshold)
    // assert done for one clk_de cycle ¡ú stable since threshold=1
    done = 1;  #1000;
    done = 0;  #1000;
    if (done_input !== 1) $fatal("Debounce fail: first pulse");

    // further pulses ignored until cleared
    done = 1;  #1000;
    done = 0;  #1000;
    if (done_input !== 0) $fatal("Debounce fail: should clear after one");

    // second valid pulse after release
    done = 1;  #1000;
    done = 0;  #1000;
    if (done_input !== 1) $fatal("Debounce fail: second pulse");

    $display("All InputModule tests passed");
    #100;
    $finish;
  end

endmodule

pipelineCPU/pipelineCPU.sim/sim_1/behav/xsim/tb_InputModule.vcd
$date
   Fri May 16 00:23:58 2025
$end
$version
  2017.4
$end
$timescale
  1ps
$end
$scope module tb_InputModule $end
$var reg 1 ! clk $end
$var reg 1 " clk_de $end
$var reg 1 # rst $end
$var reg 8 $ sw_input [7:0] $end
$var reg 1 % done $end
$var wire 32 & input_data [31:0] $end
$var wire 1 ' done_input $end
$scope module uut $end
$var wire 1 ( clk $end
$var wire 1 ) clk_de $end
$var wire 1 * rst $end
$var wire 8 + sw_input [7:0] $end
$var wire 1 , done $end
$var wire 32 & input_data [31:0] $end
$var reg 1 - done_input $end
$var reg 1 . done_stable $end
$var reg 4 / done_counter [3:0] $end
$var reg 1 0 next_done_input $end
$var reg 1 1 period_done $end
$var reg 1 2 next_period_done $end
$var parameter 4 3 DEBOUNCE_THRESHOLD [3:0] $end
$upscope $end
$upscope $end
$enddefinitions $end
#0
$dumpvars
0!
0"
0#
b0 $
0%
b0 &
0'
0(
0)
0*
b0 +
0,
0-
0.
bx /
00
01
02
b1 3
$end
#5000
1!
1(
0-
01
#10000
0!
0(
#15000
1!
1(
0-
01
#20000
0!
1#
b11110000 $
b11111111111111111111111111110000 &
0(
1*
b11110000 +
#25000
1!
1(
0-
01
#30000
0!
b1111010 $
b1111010 &
0(
b1111010 +
#35000
1!
1(
0-
01
#40000
0!
1%
0(
1,
#45000
1!
1(
0-
01
#50000
0!
0(
#55000
1!
1(
0-
01
#60000
0!
0(
#65000
1!
1(
0-
01
#70000
0!
0(
#75000
1!
1(
0-
01
#80000
0!
0(
#85000
1!
1(
0-
01
#90000
0!
0(
#95000
1!
1(
0-
01
#100000
0!
0(
#105000
1!
1(
0-
01
#110000
0!
0(
#115000
1!
1(
0-
01
#120000
0!
0(
#125000
1!
1(
0-
01
#130000
0!
0(
#135000
1!
1(
0-
01
#140000
0!
0(
#145000
1!
1(
0-
01
#150000
0!
0(
#155000
1!
1(
0-
01
#160000
0!
0(
#165000
1!
1(
0-
01
#170000
0!
0(
#175000
1!
1(
0-
01
#180000
0!
0(
#185000
1!
1(
0-
01
#190000
0!
0(
#195000
1!
1(
0-
01
#200000
0!
0(
#205000
1!
1(
0-
01
#210000
0!
0(
#215000
1!
1(
0-
01
#220000
0!
0(
#225000
1!
1(
0-
01
#230000
0!
0(
#235000
1!
1(
0-
01
#240000
0!
0(
#245000
1!
1(
0-
01
#250000
0!
0(
#255000
1!
1(
0-
01
#260000
0!
0(
#265000
1!
1(
0-
01
#270000
0!
0(
#275000
1!
1(
0-
01
#280000
0!
0(
#285000
1!
1(
0-
01
#290000
0!
0(
#295000
1!
1(
0-
01
#300000
0!
0(
#305000
1!
1(
0-
01
#310000
0!
0(
#315000
1!
1(
0-
01
#320000
0!
0(
#325000
1!
1(
0-
01
#330000
0!
0(
#335000
1!
1(
0-
01
#340000
0!
0(
#345000
1!
1(
0-
01
#350000
0!
0(
#355000
1!
1(
0-
01
#360000
0!
0(
#365000
1!
1(
0-
01
#370000
0!
0(
#375000
1!
1(
0-
01
#380000
0!
0(
#385000
1!
1(
0-
01
#390000
0!
0(
#395000
1!
1(
0-
01
#400000
0!
0(
#405000
1!
1(
0-
01
#410000
0!
0(
#415000
1!
1(
0-
01
#420000
0!
0(
#425000
1!
1(
0-
01
#430000
0!
0(
#435000
1!
1(
0-
01
#440000
0!
0(
#445000
1!
1(
0-
01
#450000
0!
0(
#455000
1!
1(
0-
01
#460000
0!
0(
#465000
1!
1(
0-
01
#470000
0!
0(
#475000
1!
1(
0-
01
#480000
0!
0(
#485000
1!
1(
0-
01
#490000
0!
0(
#495000
1!
1(
0-
01
#500000
0!
1"
0(
1)
1.
10
#505000
1!
1'
1(
1-
00
01
12
#510000
0!
0(
#515000
1!
0'
1(
0-
11
#520000
0!
0(
#525000
1!
1(
0-
11
#530000
0!
0(
#535000
1!
1(
0-
11
#540000
0!
0(
#545000
1!
1(
0-
11
#550000
0!
0(
#555000
1!
1(
0-
11
#560000
0!
0(
#565000
1!
1(
0-
11
#570000
0!
0(
#575000
1!
1(
0-
11
#580000
0!
0(
#585000
1!
1(
0-
11
#590000
0!
0(
#595000
1!
1(
0-
11
#600000
0!
0(
#605000
1!
1(
0-
11
#610000
0!
0(
#615000
1!
1(
0-
11
#620000
0!
0(
#625000
1!
1(
0-
11
#630000
0!
0(
#635000
1!
1(
0-
11
#640000
0!
0(
#645000
1!
1(
0-
11
#650000
0!
0(
#655000
1!
1(
0-
11
#660000
0!
0(
#665000
1!
1(
0-
11
#670000
0!
0(
#675000
1!
1(
0-
11
#680000
0!
0(
#685000
1!
1(
0-
11
#690000
0!
0(
#695000
1!
1(
0-
11
#700000
0!
0(
#705000
1!
1(
0-
11
#710000
0!
0(
#715000
1!
1(
0-
11
#720000
0!
0(
#725000
1!
1(
0-
11
#730000
0!
0(
#735000
1!
1(
0-
11
#740000
0!
0(
#745000
1!
1(
0-
11
#750000
0!
0(
#755000
1!
1(
0-
11
#760000
0!
0(
#765000
1!
1(
0-
11
#770000
0!
0(
#775000
1!
1(
0-
11
#780000
0!
0(
#785000
1!
1(
0-
11
#790000
0!
0(
#795000
1!
1(
0-
11
#800000
0!
0(
#805000
1!
1(
0-
11
#810000
0!
0(
#815000
1!
1(
0-
11
#820000
0!
0(
#825000
1!
1(
0-
11
#830000
0!
0(
#835000
1!
1(
0-
11
#840000
0!
0(
#845000
1!
1(
0-
11
#850000
0!
0(
#855000
1!
1(
0-
11
#860000
0!
0(
#865000
1!
1(
0-
11
#870000
0!
0(
#875000
1!
1(
0-
11
#880000
0!
0(
#885000
1!
1(
0-
11
#890000
0!
0(
#895000
1!
1(
0-
11
#900000
0!
0(
#905000
1!
1(
0-
11
#910000
0!
0(
#915000
1!
1(
0-
11
#920000
0!
0(
#925000
1!
1(
0-
11
#930000
0!
0(
#935000
1!
1(
0-
11
#940000
0!
0(
#945000
1!
1(
0-
11
#950000
0!
0(
#955000
1!
1(
0-
11
#960000
0!
0(
#965000
1!
1(
0-
11
#970000
0!
0(
#975000
1!
1(
0-
11
#980000
0!
0(
#985000
1!
1(
0-
11
#990000
0!
0(
#995000
1!
1(
0-
11
